<Config Version="4">
   <Robot Name="MTML" NumOfActuator="7" NumOfJoint="7" SN="73298">
      <Actuator ActuatorID="0" AxisID="0" BoardID="4" Type="Revolute">
         <Drive>
            <AmpsToBits Offset="32908" Scale="-5242.88" />
            <BitsToFeedbackAmps Offset="6.244791" Scale="-0.000190738" />
            <NmToAmps Scale="0.360054" />
            <MaxCurrent Unit="A" Value="0.670" />
         </Drive>
         <Encoder>
            <BitsToPosSI Scale="-0.00141933" Unit="deg" />
         </Encoder>
         <AnalogIn>
            <BitsToVolts Offset="0" Scale="6.86646e-05" />
            <VoltsToPosSI Offset="-155.435325642" Scale="75.1768567882" Unit="deg" />
         </AnalogIn>
      </Actuator>
      <Actuator ActuatorID="1" AxisID="1" BoardID="4" Type="Revolute">
         <Drive>
            <AmpsToBits Offset="32899" Scale="5242.88" />
            <BitsToFeedbackAmps Offset="-6.262765" Scale="0.000190738" />
            <NmToAmps Scale="0.457720" />
            <MaxCurrent Unit="A" Value="0.670" />
         </Drive>
         <Encoder>
            <BitsToPosSI Scale="0.00180433" Unit="deg" />
         </Encoder>
         <AnalogIn>
            <BitsToVolts Offset="0" Scale="6.86646e-05" />
            <VoltsToPosSI Offset="-142.970213388" Scale="75.7258362915" Unit="deg" />
         </AnalogIn>
      </Actuator>
      <Actuator ActuatorID="2" AxisID="2" BoardID="4" Type="Revolute">
         <Drive>
            <AmpsToBits Offset="32931" Scale="5242.88" />
            <BitsToFeedbackAmps Offset="-6.252140" Scale="0.000190738" />
            <NmToAmps Scale="0.382238" />
            <MaxCurrent Unit="A" Value="0.670" />
         </Drive>
         <Encoder>
            <BitsToPosSI Scale="0.00150678" Unit="deg" />
         </Encoder>
         <AnalogIn>
            <BitsToVolts Offset="0" Scale="6.86646e-05" />
            <VoltsToPosSI Offset="-163.412032923" Scale="76.3280215318" Unit="deg" />
         </AnalogIn>
      </Actuator>
      <Actuator ActuatorID="3" AxisID="3" BoardID="4" Type="Revolute">
         <Drive>
            <AmpsToBits Offset="32925" Scale="5242.88" />
            <BitsToFeedbackAmps Offset="-6.253442" Scale="0.000190738" />
            <NmToAmps Scale="2.168191" />
            <MaxCurrent Unit="A" Value="0.670" />
         </Drive>
         <Encoder>
            <BitsToPosSI Scale="0.00854701" Unit="deg" />
         </Encoder>
         <AnalogIn>
            <BitsToVolts Offset="0" Scale="6.86646e-05" />
            <VoltsToPosSI Offset="115.979294995" Scale="-76.840722348" Unit="deg" />
         </AnalogIn>
      </Actuator>
      <Actuator ActuatorID="4" AxisID="0" BoardID="5" Type="Revolute">
         <Drive>
            <AmpsToBits Offset="33034" Scale="-5242.88" />
            <BitsToFeedbackAmps Offset="6.261988" Scale="-0.000190738" />
            <NmToAmps Scale="6.092286" />
            <MaxCurrent Unit="A" Value="0.590" />
         </Drive>
         <Encoder>
            <BitsToPosSI Scale="-0.16963209" Unit="deg" />
         </Encoder>
         <AnalogIn>
            <BitsToVolts Offset="0" Scale="6.86646e-05" />
            <VoltsToPosSI Offset="223.58294578" Scale="-75.2268133152" Unit="deg" />
         </AnalogIn>
      </Actuator>
      <Actuator ActuatorID="5" AxisID="1" BoardID="5" Type="Revolute">
         <Drive>
            <AmpsToBits Offset="33023" Scale="5242.88" />
            <BitsToFeedbackAmps Offset="-6.268890" Scale="0.000190738" />
            <NmToAmps Scale="6.092286" />
            <MaxCurrent Unit="A" Value="0.590" />
         </Drive>
         <Encoder>
            <BitsToPosSI Scale="0.16963209" Unit="deg" />
         </Encoder>
         <AnalogIn>
            <BitsToVolts Offset="0" Scale="6.86646e-05" />
            <VoltsToPosSI Offset="-180.166063565" Scale="80.5321664942" Unit="deg" />
         </AnalogIn>
      </Actuator>
      <Actuator ActuatorID="6" AxisID="2" BoardID="5" Type="Revolute">
         <Drive>
            <AmpsToBits Offset="32948" Scale="-5242.88" />
            <BitsToFeedbackAmps Offset="6.247426" Scale="-0.000190738" />
            <NmToAmps Scale="17.791632" />
            <MaxCurrent Unit="A" Value="0.407" />
         </Drive>
         <Encoder>
            <BitsToPosSI Scale="-0.33926417" Unit="deg" />
         </Encoder>
         <AnalogIn>
            <BitsToVolts Offset="0" Scale="6.86646e-05" />
            <VoltsToPosSI Offset="-104.033440664" Scale="43.6016187846" Unit="deg" />
         </AnalogIn>
      </Actuator>
      <Potentiometers Position="Joints">
         <Tolerance Axis="0" Distance="5.00" Latency="0.01" Unit="deg" />
         <Tolerance Axis="1" Distance="5.00" Latency="0.01" Unit="deg" />
         <Tolerance Axis="2" Distance="5.00" Latency="0.01" Unit="deg" />
         <Tolerance Axis="3" Distance="5.00" Latency="0.01" Unit="deg" />
         <Tolerance Axis="4" Distance="20.00" Latency="0.03" Unit="deg" />
         <Tolerance Axis="5" Distance="20.00" Latency="0.03" Unit="deg" />
         <Tolerance Axis="6" Distance="0.00" Latency="0.00" Unit="deg" />
      </Potentiometers>
      <Coupling Value="1">
         <ActuatorToJointPosition>
            <Row Val="1.0000 0.0000 0.0000 0.0000 0.0000 0.0000 0.0000" />
            <Row Val="0.0000 1.0000 0.0000 0.0000 0.0000 0.0000 0.0000" />
            <Row Val="0.0000 -1.0000 1.0000 0.0000 0.0000 0.0000 0.0000" />
            <Row Val="0.0000 0.6697 -0.6697 1.0000 0.0000 0.0000 0.0000" />
            <Row Val="0.0000 0.0000 0.0000 0.0000 1.0000 0.0000 0.0000" />
            <Row Val="0.0000 0.0000 0.0000 0.0000 0.0000 1.0000 0.0000" />
            <Row Val="0.0000 0.0000 0.0000 0.0000 0.0000 0.0000 1.0000" />
         </ActuatorToJointPosition>
      </Coupling>
   </Robot>
</Config>